ethosian/__init__.py
ethosian/constants.py
ethosian/py.typed
ethosian/agent/__init__.py
ethosian/agent/agent.py
ethosian/agent/duckdb.py
ethosian/agent/python.py
ethosian/agent/session.py
ethosian/api/__init__.py
ethosian/api/agent.py
ethosian/api/api.py
ethosian/api/assistant.py
ethosian/api/playground.py
ethosian/api/prompt.py
ethosian/api/routes.py
ethosian/api/team.py
ethosian/api/user.py
ethosian/api/workspace.py
ethosian/api/schemas/__init__.py
ethosian/api/schemas/agent.py
ethosian/api/schemas/ai.py
ethosian/api/schemas/assistant.py
ethosian/api/schemas/monitor.py
ethosian/api/schemas/playground.py
ethosian/api/schemas/prompt.py
ethosian/api/schemas/response.py
ethosian/api/schemas/team.py
ethosian/api/schemas/user.py
ethosian/api/schemas/workspace.py
ethosian/app/__init__.py
ethosian/app/base.py
ethosian/app/context.py
ethosian/app/db_app.py
ethosian/app/group.py
ethosian/assistant/__init__.py
ethosian/assistant/assistant.py
ethosian/assistant/duckdb.py
ethosian/assistant/python.py
ethosian/assistant/run.py
ethosian/assistant/openai/__init__.py
ethosian/assistant/openai/assistant.py
ethosian/assistant/openai/exceptions.py
ethosian/assistant/openai/message.py
ethosian/assistant/openai/row.py
ethosian/assistant/openai/run.py
ethosian/assistant/openai/thread.py
ethosian/assistant/openai/tool.py
ethosian/assistant/openai/file/__init__.py
ethosian/assistant/openai/file/file.py
ethosian/assistant/openai/file/local.py
ethosian/assistant/openai/file/url.py
ethosian/aws/__init__.py
ethosian/aws/api_client.py
ethosian/aws/resources.py
ethosian/aws/app/__init__.py
ethosian/aws/app/base.py
ethosian/aws/app/context.py
ethosian/aws/app/django/__init__.py
ethosian/aws/app/django/django.py
ethosian/aws/app/fastapi/__init__.py
ethosian/aws/app/fastapi/fastapi.py
ethosian/aws/app/jupyter/__init__.py
ethosian/aws/app/jupyter/jupyter.py
ethosian/aws/app/qdrant/__init__.py
ethosian/aws/app/qdrant/qdrant.py
ethosian/aws/app/streamlit/__init__.py
ethosian-0.1.1.dist-info/LICENSE
ethosian-0.1.1.dist-info/METADATA
ethosian-0.1.1.dist-info/WHEEL
ethosian-0.1.1.dist-info/entry_points.txt
ethosian-0.1.1.dist-info/top_level.txt
ethosian-0.1.1.dist-info/RECORD
